trywebscraping/__init__.py
trywebscraping/api_key.py
trywebscraping/base_scraper.py
trywebscraping/browse.py
trywebscraping/cli.py
trywebscraping/fetch.py
trywebscraping/query.py
trywebscraping/utils.py
trywebscraping-0.1.37.dist-info/METADATA
trywebscraping-0.1.37.dist-info/WHEEL
trywebscraping-0.1.37.dist-info/entry_points.txt
trywebscraping-0.1.37.dist-info/top_level.txt
trywebscraping-0.1.37.dist-info/RECORD
