Metadata-Version: 2.1
Name: trywebscraping
Version: 0.1.37
Summary: A fast web scraping library
Home-page: https://github.com/yourusername/trywebscraping
Author: Luke Lucas
Author-email: luke.lucas@trywebscraping.com
License: UNKNOWN
Platform: UNKNOWN
Classifier: Programming Language :: Python :: 3
Classifier: License :: OSI Approved :: MIT License
Classifier: Operating System :: OS Independent
Requires-Python: >=3.7
Requires-Dist: requests
Requires-Dist: beautifulsoup4
Requires-Dist: lxml
Requires-Dist: selenium
Requires-Dist: webdriver-manager
Requires-Dist: click
Requires-Dist: cryptography
Requires-Dist: curl-cffi
Requires-Dist: twine
Provides-Extra: dev
Requires-Dist: pytest; extra == "dev"
Requires-Dist: pytest-cov; extra == "dev"
Requires-Dist: flake8; extra == "dev"
Requires-Dist: black; extra == "dev"
Requires-Dist: isort; extra == "dev"
